{
  "data": {
    "article": {},
    "attachments": {},
    "author_id": "2045513838850641921",
    "conversation_id": "2075744867897241886",
    "created_at": "2026-07-11T18:57:14.000Z",
    "edit_controls": {
      "editable_until": "2026-07-11T19:57:14.000Z",
      "edits_remaining": 5,
      "is_edit_eligible": false
    },
    "edit_history_tweet_ids": [
      "2076017993776324863"
    ],
    "entities": {
      "mentions": [
        {
          "end": 10,
          "id": "2061329105266831360",
          "start": 0,
          "username": "yangion73"
        }
      ]
    },
    "geo": {},
    "id": "2076017993776324863",
    "in_reply_to_user_id": "2061329105266831360",
    "lang": "zh",
    "note_tweet": {
      "entities": {}
    },
    "possibly_sensitive": false,
    "public_metrics": {
      "bookmark_count": 0,
      "impression_count": 0,
      "like_count": 0,
      "quote_count": 0,
      "reply_count": 0,
      "retweet_count": 0
    },
    "referenced_tweets": [
      {
        "id": "2075744867897241886",
        "type": "replied_to"
      }
    ],
    "reply_settings": "everyone",
    "text": "@yangion73 不用紧张哦，小症算好开的，基本上实话实说就行，pass不pass无所谓医生不在意"
  },
  "includes": {
    "tweets": [
      {
        "article": {},
        "attachments": {},
        "author_id": "2045513838850641921",
        "conversation_id": "2075744867897241886",
        "created_at": "2026-07-11T18:57:14.000Z",
        "edit_controls": {
          "editable_until": "2026-07-11T19:57:14.000Z",
          "edits_remaining": 5,
          "is_edit_eligible": false
        },
        "edit_history_tweet_ids": [
          "2076017993776324863"
        ],
        "entities": {
          "mentions": [
            {
              "end": 10,
              "id": "2061329105266831360",
              "start": 0,
              "username": "yangion73"
            }
          ]
        },
        "geo": {},
        "id": "2076017993776324863",
        "in_reply_to_user_id": "2061329105266831360",
        "lang": "zh",
        "note_tweet": {
          "entities": {}
        },
        "possibly_sensitive": false,
        "public_metrics": {
          "bookmark_count": 0,
          "impression_count": 0,
          "like_count": 0,
          "quote_count": 0,
          "reply_count": 0,
          "retweet_count": 0
        },
        "referenced_tweets": [
          {
            "id": "2075744867897241886",
            "type": "replied_to"
          }
        ],
        "reply_settings": "everyone",
        "text": "@yangion73 不用紧张哦，小症算好开的，基本上实话实说就行，pass不pass无所谓医生不在意"
      },
      {
        "article": {},
        "attachments": {},
        "author_id": "2061329105266831360",
        "conversation_id": "2075744867897241886",
        "created_at": "2026-07-11T00:51:56.000Z",
        "edit_controls": {
          "editable_until": "2026-07-11T01:51:56.000Z",
          "edits_remaining": 5,
          "is_edit_eligible": true
        },
        "edit_history_tweet_ids": [
          "2075744867897241886"
        ],
        "entities": {},
        "geo": {},
        "id": "2075744867897241886",
        "lang": "zh",
        "note_tweet": {
          "entities": {}
        },
        "possibly_sensitive": false,
        "public_metrics": {
          "bookmark_count": 0,
          "impression_count": 1295,
          "like_count": 31,
          "quote_count": 0,
          "reply_count": 7,
          "retweet_count": 0
        },
        "reply_settings": "everyone",
        "text": "好紧张，明天就要去上海精卫了，完全不知道过去要怎么说，万一连小证都没开出来这次就白跑这么远了🥲\n而且我还没成年，外表也不够 pass， 大概率吕姐也不会开，白跑这么一趟真的不甘心怎么办啊😭\n有没有去过的同类教教我要怎么说呀"
      }
    ],
    "users": [
      {
        "created_at": "2026-04-18T14:47:16.000Z",
        "derived": {
          "locations": [
            {
              "country_code": "KR",
              "full_name": "Tenan, South Chungcheong, Korea (Republic of)",
              "geo": {
                "coordinates": [
                  127.1522,
                  36.8065
                ],
                "type": "Point"
              },
              "locality": "Tenan",
              "region": "South Chungcheong"
            }
          ]
        },
        "description": "前世@inlineint /mtx?/HRT2026.3.9/小证2026.4.12/INTP/中焦重抑/前ODer/高中生长假中/OIer/音游人/CNCSer/MC/不键政/看成分互fo/发发梗图/是猫娘喵～",
        "entities": {
          "description": {
            "mentions": [
              {
                "end": 12,
                "start": 2,
                "username": "inlineint"
              }
            ]
          },
          "url": {
            "urls": [
              {
                "display_url": "ngl.link/inlineint",
                "end": 23,
                "expanded_url": "https://ngl.link/inlineint",
                "start": 0,
                "url": "https://t.co/llFM5urW6q"
              }
            ]
          }
        },
        "id": "2045513838850641921",
        "location": "天国",
        "name": "int喵喵喵🍥",
        "pinned_tweet_id": "2068232879453192300",
        "profile_image_url": "https://pbs.twimg.com/profile_images/2064010530184990720/ZPdr6smn_normal.jpg",
        "protected": false,
        "public_metrics": {
          "followers_count": 1320,
          "following_count": 1089,
          "like_count": 2043,
          "listed_count": 3,
          "media_count": 194,
          "tweet_count": 621
        },
        "url": "https://t.co/llFM5urW6q",
        "username": "inline_int",
        "verified": true
      },
      {
        "created_at": "2026-06-01T06:09:24.000Z",
        "description": "MTF 🏳️‍⚧️ | HRT 🍥2026.4.13 无证含糖\n出厂日期 2011.5.17 |家长反对党 |\n| od | 紫残| 精神状态堪忧|重抑重焦|\n续上糖了(开心☺️)\n 欢迎互 fo 呀\n同类有看见必回 fo",
        "id": "2061329105266831360",
        "name": "溯音 🍥",
        "profile_image_url": "https://pbs.twimg.com/profile_images/2063942814141214720/JsJbUJSH_normal.jpg",
        "protected": false,
        "public_metrics": {
          "followers_count": 336,
          "following_count": 181,
          "like_count": 185,
          "listed_count": 1,
          "media_count": 61,
          "tweet_count": 336
        },
        "url": "",
        "username": "yangion73",
        "verified": false
      }
    ]
  }
}