{
  "data": {
    "article": {},
    "attachments": {},
    "author_id": "2045513838850641921",
    "conversation_id": "2051504497978138906",
    "created_at": "2026-05-05T04:07:18.000Z",
    "edit_controls": {
      "editable_until": "2026-05-05T05:07:18.000Z",
      "edits_remaining": 5,
      "is_edit_eligible": false
    },
    "edit_history_tweet_ids": [
      "2051514045547598191"
    ],
    "entities": {
      "mentions": [
        {
          "end": 11,
          "id": "1900108524304076800",
          "start": 0,
          "username": "qi_bu64350"
        }
      ]
    },
    "geo": {},
    "id": "2051514045547598191",
    "in_reply_to_user_id": "1900108524304076800",
    "lang": "ja",
    "note_tweet": {
      "entities": {}
    },
    "possibly_sensitive": false,
    "public_metrics": {
      "bookmark_count": 0,
      "impression_count": 0,
      "like_count": 0,
      "quote_count": 0,
      "reply_count": 0,
      "retweet_count": 0
    },
    "referenced_tweets": [
      {
        "id": "2051504497978138906",
        "type": "replied_to"
      }
    ],
    "reply_settings": "everyone",
    "text": "@qi_bu64350 炒股"
  },
  "includes": {
    "tweets": [
      {
        "article": {},
        "attachments": {},
        "author_id": "2045513838850641921",
        "conversation_id": "2051504497978138906",
        "created_at": "2026-05-05T04:07:18.000Z",
        "edit_controls": {
          "editable_until": "2026-05-05T05:07:18.000Z",
          "edits_remaining": 5,
          "is_edit_eligible": false
        },
        "edit_history_tweet_ids": [
          "2051514045547598191"
        ],
        "entities": {
          "mentions": [
            {
              "end": 11,
              "id": "1900108524304076800",
              "start": 0,
              "username": "qi_bu64350"
            }
          ]
        },
        "geo": {},
        "id": "2051514045547598191",
        "in_reply_to_user_id": "1900108524304076800",
        "lang": "ja",
        "note_tweet": {
          "entities": {}
        },
        "possibly_sensitive": false,
        "public_metrics": {
          "bookmark_count": 0,
          "impression_count": 0,
          "like_count": 0,
          "quote_count": 0,
          "reply_count": 0,
          "retweet_count": 0
        },
        "referenced_tweets": [
          {
            "id": "2051504497978138906",
            "type": "replied_to"
          }
        ],
        "reply_settings": "everyone",
        "text": "@qi_bu64350 炒股"
      },
      {
        "article": {},
        "attachments": {},
        "author_id": "1900108524304076800",
        "conversation_id": "2051504497978138906",
        "created_at": "2026-05-05T03:29:22.000Z",
        "edit_controls": {
          "editable_until": "2026-05-05T04:29:22.000Z",
          "edits_remaining": 5,
          "is_edit_eligible": true
        },
        "edit_history_tweet_ids": [
          "2051504497978138906"
        ],
        "entities": {},
        "geo": {},
        "id": "2051504497978138906",
        "lang": "zh",
        "note_tweet": {
          "entities": {}
        },
        "possibly_sensitive": false,
        "public_metrics": {
          "bookmark_count": 0,
          "impression_count": 380,
          "like_count": 20,
          "quote_count": 2,
          "reply_count": 11,
          "retweet_count": 0
        },
        "reply_settings": "everyone",
        "text": "有没有什么能快速赚很多钱的方法（）"
      }
    ],
    "users": [
      {
        "created_at": "2026-04-18T14:47:16.000Z",
        "description": "前世@inlineint /HRT2026.3.9🍥/小证2026.4.12/INTP/已炸柜/家长党/中抑中焦/OD/高中生/OIer/彩笔音游人rks15.46/计算机狂热爱好者/不键政/看成分互fo/是猫娘喵～",
        "entities": {
          "description": {
            "mentions": [
              {
                "end": 12,
                "start": 2,
                "username": "inlineint"
              }
            ]
          },
          "url": {
            "urls": [
              {
                "display_url": "ngl.link/inlineint",
                "end": 23,
                "expanded_url": "https://ngl.link/inlineint",
                "start": 0,
                "url": "https://t.co/llFM5urogS"
              }
            ]
          }
        },
        "id": "2045513838850641921",
        "location": "天堂",
        "name": "int喵🏳️‍⚧️🍥",
        "profile_image_url": "https://pbs.twimg.com/profile_images/2045515096600748032/ZOpNMKpP_normal.jpg",
        "protected": false,
        "public_metrics": {
          "followers_count": 462,
          "following_count": 515,
          "like_count": 422,
          "listed_count": 0,
          "media_count": 25,
          "tweet_count": 114
        },
        "url": "https://t.co/llFM5urogS",
        "username": "inline_int",
        "verified": true
      },
      {
        "created_at": "2025-03-13T08:56:07.000Z",
        "description": "好累……\n依旧把这当QQ空间用\n一切过激言论均由第二人格控制发布\n前@Ciallo_114_514 @YunoQiu56649",
        "entities": {
          "description": {
            "mentions": [
              {
                "end": 49,
                "start": 34,
                "username": "Ciallo_114_514"
              },
              {
                "end": 63,
                "start": 50,
                "username": "YunoQiu56649"
              }
            ]
          }
        },
        "id": "1900108524304076800",
        "location": "第五高原",
        "name": "Ciallo～(∠・ω ≤ )︵★🍥🏳️‍⚧️",
        "pinned_tweet_id": "2049667185740775911",
        "profile_image_url": "https://pbs.twimg.com/profile_images/2049695578402304000/1dyUSXys_normal.jpg",
        "protected": false,
        "public_metrics": {
          "followers_count": 533,
          "following_count": 580,
          "like_count": 547,
          "listed_count": 2,
          "media_count": 19,
          "tweet_count": 742
        },
        "username": "qi_bu64350",
        "verified": false
      }
    ]
  }
}